[
    {
        "model": "cart.orderitems",
        "pk": 3,
        "fields": {
            "order": 3,
            "book": 2,
            "quantity": 2
        }
    },
    {
        "model": "cart.orderitems",
        "pk": 4,
        "fields": {
            "order": 3,
            "book": 1,
            "quantity": 2
        }
    },
    {
        "model": "cart.orderitems",
        "pk": 6,
        "fields": {
            "order": 4,
            "book": 3,
            "quantity": 2
        }
    },
    {
        "model": "cart.orderitems",
        "pk": 7,
        "fields": {
            "order": 4,
            "book": 4,
            "quantity": 2
        }
    },
    {
        "model": "cart.orderitems",
        "pk": 8,
        "fields": {
            "order": 5,
            "book": 1,
            "quantity": 1
        }
    },
    {
        "model": "cart.orderitems",
        "pk": 9,
        "fields": {
            "order": 6,
            "book": 2,
            "quantity": 2
        }
    },
    {
        "model": "cart.orderitems",
        "pk": 10,
        "fields": {
            "order": 7,
            "book": 1,
            "quantity": 1
        }
    },
    {
        "model": "cart.orderitems",
        "pk": 11,
        "fields": {
            "order": 7,
            "book": 2,
            "quantity": 1
        }
    },
    {
        "model": "cart.orderitems",
        "pk": 12,
        "fields": {
            "order": 7,
            "book": 3,
            "quantity": 2
        }
    },
    {
        "model": "cart.orderitems",
        "pk": 13,
        "fields": {
            "order": 9,
            "book": 2,
            "quantity": 1
        }
    },
    {
        "model": "cart.orderitems",
        "pk": 14,
        "fields": {
            "order": 9,
            "book": 1,
            "quantity": 2
        }
    },
    {
        "model": "cart.orderitems",
        "pk": 15,
        "fields": {
            "order": 10,
            "book": 2,
            "quantity": 1
        }
    },
    {
        "model": "cart.orderitems",
        "pk": 16,
        "fields": {
            "order": 11,
            "book": 4,
            "quantity": 2
        }
    },
    {
        "model": "cart.orderitems",
        "pk": 17,
        "fields": {
            "order": 12,
            "book": 1,
            "quantity": 1
        }
    },
    {
        "model": "cart.orderitems",
        "pk": 18,
        "fields": {
            "order": 12,
            "book": 2,
            "quantity": 1
        }
    },
    {
        "model": "cart.orderitems",
        "pk": 19,
        "fields": {
            "order": 14,
            "book": 2,
            "quantity": 1
        }
    },
    {
        "model": "cart.orderitems",
        "pk": 20,
        "fields": {
            "order": 14,
            "book": 3,
            "quantity": 2
        }
    },
    {
        "model": "cart.orderitems",
        "pk": 21,
        "fields": {
            "order": 15,
            "book": 1,
            "quantity": 1
        }
    },
    {
        "model": "cart.orderitems",
        "pk": 22,
        "fields": {
            "order": 15,
            "book": 2,
            "quantity": 1
        }
    },
    {
        "model": "cart.orderitems",
        "pk": 23,
        "fields": {
            "order": 17,
            "book": 2,
            "quantity": 1
        }
    },
    {
        "model": "cart.orderitems",
        "pk": 24,
        "fields": {
            "order": 17,
            "book": 1,
            "quantity": 2
        }
    },
    {
        "model": "cart.orderitems",
        "pk": 25,
        "fields": {
            "order": 18,
            "book": 1,
            "quantity": 2
        }
    },
    {
        "model": "cart.orderitems",
        "pk": 26,
        "fields": {
            "order": 19,
            "book": 2,
            "quantity": 1
        }
    },
    {
        "model": "cart.orderitems",
        "pk": 27,
        "fields": {
            "order": 19,
            "book": 1,
            "quantity": 2
        }
    },
    {
        "model": "cart.orderitems",
        "pk": 28,
        "fields": {
            "order": 20,
            "book": 2,
            "quantity": 1
        }
    },
    {
        "model": "cart.orderitems",
        "pk": 29,
        "fields": {
            "order": 20,
            "book": 3,
            "quantity": 3
        }
    },
    {
        "model": "cart.orderitems",
        "pk": 30,
        "fields": {
            "order": 20,
            "book": 1,
            "quantity": 1
        }
    }
]